{
  "title": "Invoice",
  "invoice_number": "INV872679",
  "patient_id": null,
  "invoice_date": "12-14-1993",
  "due_date": "01-13-1994",
  "patient_name": "Taylor Parsons",
  "patient_age": null,
  "patient_address": "22162 Renee Canyon, South Ronaldville, MN 50745",
  "patient_phone": "1-234-567-8900",
  "patient_email": "info@whitepetalhospital.org",
  "admission_date": null,
  "discharge_date": null,
  "subtotal_amount": 55.0,
  "discount_amount": 16.5,
  "total_amount": 40.98,
  "provider_name": null,
  "bed_id": null,
  "line_items": [
    {
      "description": "Vaccination Booster",
      "code": "VB08",
      "amount": 55.0
    }
  ]
}